TOPSIS/__init__.py
TOPSIS/topsis.py
Topsis_Devansh_102203449-0.1.dist-info/LICENSE
Topsis_Devansh_102203449-0.1.dist-info/METADATA
Topsis_Devansh_102203449-0.1.dist-info/WHEEL
Topsis_Devansh_102203449-0.1.dist-info/entry_points.txt
Topsis_Devansh_102203449-0.1.dist-info/top_level.txt
Topsis_Devansh_102203449-0.1.dist-info/RECORD
