Metadata-Version: 2.1
Name: Topsis-Devansh-102203449
Version: 0.1
Summary: A TOPSIS implementation package for Multiple Criteria Decision Making
Home-page: https://github.com/devanshdhir2/topsis-pypi-package
Author: Devansh Dhir
Author-email: dhir.devansh@gmail.com
License: UNKNOWN
Platform: UNKNOWN
Classifier: Programming Language :: Python :: 3
Classifier: License :: OSI Approved :: MIT License
Classifier: Operating System :: OS Independent
Requires-Python: >=3.6
License-File: LICENSE
Requires-Dist: pandas
Requires-Dist: numpy
